[
    {
        "note_id": "4315",
        "date": "3.10.2021 @ 15:00:53",
        "title": "Complete residential investment report",
        "text": "✅   Complete draft report.\n  Distribute draft for comments.\n  Complete final version and issue for distribution. "
    },
    {
        "note_id": "40c1d",
        "date": "3.10.2021 @ 15:10:53",
        "title": "Complete investor presentation",
        "text": "Draft investor presentation needs to be completed no later than Friday 19-Nov-21. "
    }
]